cologs.py
cologs-0.3.dist-info/LICENSE
cologs-0.3.dist-info/WHEEL
cologs-0.3.dist-info/METADATA
cologs-0.3.dist-info/RECORD
