Metadata-Version: 2.1
Name: cologs
Version: 0.3
Summary: Colorful and Simple Logger: cologs
Author-email: nullscry <nullscry@nullscry.com>
Classifier: License :: OSI Approved :: GNU General Public License v3 or later (GPLv3+)
Project-URL: Home, https://github.com/nullscry
